{"is_source_file": true, "format": "Python", "description": "This file defines a workflow for fetching top stories from Hacker News, generating a report, and formatting it as a news article. It includes classes and methods for retrieving data from Hacker News API, processing articles, and producing a structured report.", "external_files": ["agno.agent", "agno.tools.newspaper4k", "agno.utils.log", "agno.utils.pprint", "agno.workflow", "httpx"], "external_methods": ["httpx.get", "logger.info", "pprint_run_response", "RunResponse", "Agent", "Workflow"], "published": ["HackerNewsReporter"], "classes": [{"name": "HackerNewsReporter", "description": "A workflow class that fetches top Hacker News stories, generates a detailed report, and formats it for presentation."}], "methods": [{"name": "get_top_hackernews_stories", "description": "Fetches top stories from Hacker News API and returns them as a JSON string."}, {"name": "run", "description": "Executes the workflow: retrieves top stories, generates a report, and yields formatted responses."}], "calls": ["httpx.get", "logger.info", "self.hn_agent.run", "self.writer.run", "pprint_run_response"], "search-terms": ["HackerNewsReporter", "get_top_hackernews_stories", "Hacker News API", "news report workflow", "hackernews top stories"], "state": 2, "file_id": 1595, "knowledge_revision": 3837, "git_revision": "e67ee577664da81d64486d0682baa2083ae8659b", "ctags": [], "filename": "cookbook/workflows/hackernews_reporter.py", "hash": "d9b63c923846d62ba37e932d1170aa0b", "format-version": 4, "code-base-name": "https://github.com/codesperfect/agno.git:main", "revision_history": [{"3837": "e67ee577664da81d64486d0682baa2083ae8659b"}]}