{"is_source_file": true, "format": "Python", "description": "This file defines a data model for a movie script using Pydantic, and sets up an agent that utilizes a Llama model to generate structured output based on the MovieScript schema.", "external_files": ["agno.agent", "agno.models.meta", "pydantic", "rich.pretty"], "external_methods": ["Agent", "RunResponse", "Llama", "BaseModel", "Field", "pprint"], "published": ["json_schema_output_agent"], "classes": [{"name": "MovieScript", "description": "A Pydantic model representing the structure of a movie script, including setting, ending, genre, name, characters, and storyline."}], "methods": [{"name": "print_response", "description": "Method of the Agent class used to generate and print a response based on input, here invoked with 'New York'."}], "calls": ["Agent", "json_schema_output_agent.print_response"], "search-terms": ["MovieScript", "Llama-4-Maverick-17B-128E-Instruct-FP8", "structured_output", "agent", "pydantic model"], "state": 2, "file_id": 1472, "knowledge_revision": 3741, "git_revision": "d9eca7f6730a3a3af6ec01aa707f06507128cd9e", "ctags": [], "filename": "cookbook/models/meta/llama/structured_output.py", "hash": "d729ed12d969d6ddc60d56de9c801033", "format-version": 4, "code-base-name": "https://github.com/codesperfect/agno.git:main", "revision_history": [{"3741": "d9eca7f6730a3a3af6ec01aa707f06507128cd9e"}]}