{"is_source_file": true, "format": "Python", "description": "This file defines the SerperTools class, a Python module that provides methods to interact with the Serper API for Google search, news, scholar, and webpage scraping functionalities. It includes request handling, API interaction, and logging.", "external_files": ["requests", "agno.tools", "agno.utils.log"], "external_methods": ["requests.request", "log_debug", "log_error", "log_warning"], "published": ["SerperTools"], "classes": [{"name": "SerperTools", "description": "A class that provides methods to perform various searches and webpage scraping using the Serper API, extending the Toolkit class."}], "methods": [{"name": "__init__", "description": "Initializes the SerperTools instance with API key, location, language, number of results, and optional parameters."}, {"name": "_make_request", "description": "Handles making HTTP POST requests to the Serper API endpoints with proper headers and parameters."}, {"name": "search", "description": "Performs a Google search query via the Serper API and returns the raw JSON response."}, {"name": "search_news", "description": "Performs a news search query via the Serper API and returns the raw JSON response."}, {"name": "search_scholar", "description": "Performs an academic paper search via Google Scholar through the Serper API and returns the raw JSON response."}, {"name": "scrape_webpage", "description": "Scrapes content from a webpage URL using the Serper scraping API and returns the content in JSON format."}], "calls": ["requests.request", "log_debug", "log_error", "log_warning"], "search-terms": ["SerperTools", "Serper API", "Google search API", "webpage scraping", "news search", "scholar search"], "state": 2, "file_id": 482, "knowledge_revision": 2712, "git_revision": "a162d4dd59baa5d0d0fc274faa125577bdd50138", "ctags": [], "filename": "libs/agno/agno/tools/serper.py", "hash": "9232451905448d691558015fbc41b835", "format-version": 4, "code-base-name": "https://github.com/codesperfect/agno.git:main", "revision_history": [{"2712": "a162d4dd59baa5d0d0fc274faa125577bdd50138"}]}