{"is_source_file": true, "format": "Python", "description": "This file defines a class SQLTools that provides methods for interacting with a SQL database, including listing tables, describing table schemas, and executing SQL queries. It uses SQLAlchemy for database connections and inspection.", "external_files": ["agno.tools", "agno.utils.log"], "external_methods": ["agno.tools.Toolkit", "agno.utils.log.log_debug", "agno.utils.log.logger", "sqlalchemy.create_engine", "sqlalchemy.inspect", "sqlalchemy.orm.sessionmaker", "sqlalchemy.sql.expression.text"], "published": ["SQLTools"], "classes": [{"name": "SQLTools", "description": "A toolkit class for executing and inspecting SQL database schemas and data."}], "methods": [{"name": "list_tables", "description": "Returns a JSON string of the list of table names in the database or the provided tables dictionary."}, {"name": "describe_table", "description": "Returns a JSON string describing the columns of a specified table."}, {"name": "run_sql_query", "description": "Executes a SQL query and returns the result as a JSON string, with optional row limit."}, {"name": "run_sql", "description": "Internal method that executes a SQL statement and returns the result as a list of dictionaries."}], "calls": ["inspect(self.db_engine)", "self.run_sql(sql=query, limit=limit)", "sess.execute(text(sql))"], "search-terms": ["SQLAlchemy", "database inspection", "SQL query execution", "schema description", "list tables"], "state": 2, "file_id": 431, "knowledge_revision": 2679, "git_revision": "a738a4771a46c6dfb17a1494a80ff1dbe8e58976", "ctags": [], "filename": "libs/agno/agno/tools/sql.py", "hash": "4327e53c2e21281170f3ac287576dbbf", "format-version": 4, "code-base-name": "https://github.com/codesperfect/agno.git:main", "revision_history": [{"2679": "a738a4771a46c6dfb17a1494a80ff1dbe8e58976"}]}